{"cameraMode":{"drawMode":0,"name":"Shaded","section":"Shading Mode"},"sceneLighting":true,"audioPlay":false,"sceneViewState":{"showFog":true,"showMaterialUpdate":false,"showSkybox":true,"showFlares":true,"showImageEffects":true,"showParticleSystems":true},"in2DMode":false,"pivot":{"x":-17.663349151611329,"y":-1.826939582824707,"z":60.056419372558597},"rotation":{"x":-0.05352434143424034,"y":0.16638627648353578,"z":-0.009044792503118515,"w":-0.9845678806304932},"size":56.94582748413086,"orthographic":false}